paperpulseai/__init__.py
paperpulseai/core.py
paperpulseai/deepseek_model.py
paperpulseai-0.1.1.dist-info/LICENSE
paperpulseai-0.1.1.dist-info/METADATA
paperpulseai-0.1.1.dist-info/WHEEL
paperpulseai-0.1.1.dist-info/entry_points.txt
paperpulseai-0.1.1.dist-info/top_level.txt
paperpulseai-0.1.1.dist-info/RECORD
