Metadata-Version: 2.2
Name: paperpulseai
Version: 0.1.1
Summary: An AI-powered tool for processing and analyzing scientific papers
Home-page: https://www.semiquant.com
Author: SemiQuant
Author-email: Jason.Limberis@ucsf.edu
Classifier: Development Status :: 3 - Alpha
Classifier: Intended Audience :: Science/Research
Classifier: License :: OSI Approved :: MIT License
Classifier: Operating System :: OS Independent
Classifier: Programming Language :: Python :: 3
Classifier: Programming Language :: Python :: 3.8
Classifier: Programming Language :: Python :: 3.9
Classifier: Programming Language :: Python :: 3.10
Classifier: Programming Language :: Python :: 3.11
Requires-Python: >=3.8
License-File: LICENSE
Requires-Dist: biopython>=1.83
Requires-Dist: click>=8.1.7
Requires-Dist: diskcache>=5.6.3
Requires-Dist: pandas>=2.2.1
Requires-Dist: PyPDF2>=3.0.1
Requires-Dist: reportlab>=4.1.0
Requires-Dist: requests>=2.31.0
Requires-Dist: rich>=13.7.1
Requires-Dist: scikit-learn>=1.4.1.post1
Requires-Dist: tenacity>=8.2.3
Requires-Dist: beautifulsoup4>=4.12.3
Dynamic: author
Dynamic: author-email
Dynamic: classifier
Dynamic: description
Dynamic: description-content-type
Dynamic: home-page
Dynamic: requires-dist
Dynamic: requires-python
Dynamic: summary
